alogger/__init__.py
alogger/base.py
alogger/utils.py
alogger/parsers/__init__.py
alogger/parsers/sge.py
alogger/parsers/slurm.py
alogger/parsers/torque.py
alogger/parsers/winhpc.py
alogger/tests/__init__.py
alogger/tests/base.py
alogger/tests/test_sge.py
alogger/tests/test_slurm.py
alogger/tests/test_torque.py
alogger/tests/test_winhpc.py
alogger/tests/examples/__init__.py
alogger/tests/examples/sge.log
alogger/tests/examples/slurm.log
alogger/tests/examples/torque.log
alogger/tests/examples/winhpc.log
alogger/tests/results/__init__.py
alogger/tests/results/sge.json
alogger/tests/results/slurm.json
alogger/tests/results/torque.json
python_alogger-2.2.12.dist-info/AUTHORS.txt
python_alogger-2.2.12.dist-info/COPYING.txt
python_alogger-2.2.12.dist-info/METADATA
python_alogger-2.2.12.dist-info/WHEEL
python_alogger-2.2.12.dist-info/top_level.txt
python_alogger-2.2.12.dist-info/RECORD
