Metadata-Version: 2.1
Name: python-alogger
Version: 2.2.12
Summary: Small python library to parse resource manager logs
Home-page: https://github.com/Karaage-Cluster/python-alogger
Author: Brian May
Author-email: brian@linuxpenguins.xyz
License: GPL3+
Keywords: karaage cluster user administration
Platform: UNKNOWN
Classifier: Development Status :: 5 - Production/Stable
Classifier: Intended Audience :: Developers
Classifier: License :: OSI Approved :: GNU Lesser General Public License v3 or later (LGPLv3+)
Classifier: Operating System :: OS Independent
Classifier: Programming Language :: Python :: 3.7
Classifier: Topic :: Software Development :: Libraries :: Python Modules
